idom/__init__.py
idom/__main__.py
idom/_option.py
idom/_warnings.py
idom/config.py
idom/html.py
idom/logging.py
idom/py.typed
idom/sample.py
idom/svg.py
idom/types.py
idom/utils.py
idom/widgets.py
idom/_client/idom-logo-square-small.svg
idom/_client/index.html
idom/_client/assets/index.a2011453.js
idom/_console/__init__.py
idom/_console/ast_utils.py
idom/_console/rewrite_camel_case_props.py
idom/_console/rewrite_keys.py
idom/backend/__init__.py
idom/backend/_common.py
idom/backend/default.py
idom/backend/fastapi.py
idom/backend/flask.py
idom/backend/hooks.py
idom/backend/sanic.py
idom/backend/starlette.py
idom/backend/tornado.py
idom/backend/types.py
idom/backend/utils.py
idom/core/__init__.py
idom/core/_f_back.py
idom/core/_thread_local.py
idom/core/component.py
idom/core/events.py
idom/core/hooks.py
idom/core/layout.py
idom/core/serve.py
idom/core/types.py
idom/core/vdom.py
idom/testing/__init__.py
idom/testing/backend.py
idom/testing/common.py
idom/testing/display.py
idom/testing/logs.py
idom/web/__init__.py
idom/web/module.py
idom/web/utils.py
idom/web/templates/react.js
idom-1.0.0.dist-info/LICENSE
idom-1.0.0.dist-info/METADATA
idom-1.0.0.dist-info/WHEEL
idom-1.0.0.dist-info/entry_points.txt
idom-1.0.0.dist-info/top_level.txt
idom-1.0.0.dist-info/RECORD
