Metadata-Version: 2.1
Name: idom
Version: 1.0.0
Summary: It's React, but in Python
Home-page: https://github.com/rmorshea/idom
Author: Ryan Morshead
Author-email: ryan.morshead@gmail.com
License: MIT
Keywords: interactive,widgets,DOM,React
Platform: Linux
Platform: Mac OS X
Platform: Windows
Classifier: Environment :: Web Environment
Classifier: Framework :: AsyncIO
Classifier: Framework :: Flask
Classifier: Intended Audience :: Developers
Classifier: Intended Audience :: Science/Research
Classifier: Programming Language :: Python :: 3.7
Classifier: Programming Language :: Python :: 3.8
Classifier: Programming Language :: Python :: 3.9
Classifier: Topic :: Software Development :: User Interfaces
Classifier: Topic :: Software Development :: Widget Sets
Classifier: Typing :: Typed
Requires-Python: >=3.7
License-File: LICENSE
Requires-Dist: typing-extensions (>=3.10)
Requires-Dist: mypy-extensions (>=0.4.3)
Requires-Dist: anyio (>=3)
Requires-Dist: jsonpatch (>=1.32)
Requires-Dist: fastjsonschema (>=2.14.5)
Requires-Dist: requests (>=2)
Requires-Dist: colorlog (>=6)
Requires-Dist: asgiref (>=3)
Requires-Dist: lxml (>=4)
Provides-Extra: all
Requires-Dist: starlette (>=0.13.6) ; extra == 'all'
Requires-Dist: uvicorn[standard] (>=0.19.0) ; extra == 'all'
Requires-Dist: sanic (>=21) ; extra == 'all'
Requires-Dist: sanic-cors ; extra == 'all'
Requires-Dist: fastapi (>=0.63.0) ; extra == 'all'
Requires-Dist: flask ; extra == 'all'
Requires-Dist: markupsafe (<2.1,>=1.1.1) ; extra == 'all'
Requires-Dist: flask-cors ; extra == 'all'
Requires-Dist: flask-sock ; extra == 'all'
Requires-Dist: tornado ; extra == 'all'
Requires-Dist: playwright ; extra == 'all'
Provides-Extra: fastapi
Requires-Dist: fastapi (>=0.63.0) ; extra == 'fastapi'
Requires-Dist: uvicorn[standard] (>=0.19.0) ; extra == 'fastapi'
Provides-Extra: flask
Requires-Dist: flask ; extra == 'flask'
Requires-Dist: markupsafe (<2.1,>=1.1.1) ; extra == 'flask'
Requires-Dist: flask-cors ; extra == 'flask'
Requires-Dist: flask-sock ; extra == 'flask'
Provides-Extra: sanic
Requires-Dist: sanic (>=21) ; extra == 'sanic'
Requires-Dist: sanic-cors ; extra == 'sanic'
Requires-Dist: uvicorn[standard] (>=0.19.0) ; extra == 'sanic'
Provides-Extra: starlette
Requires-Dist: starlette (>=0.13.6) ; extra == 'starlette'
Requires-Dist: uvicorn[standard] (>=0.19.0) ; extra == 'starlette'
Provides-Extra: testing
Requires-Dist: playwright ; extra == 'testing'
Provides-Extra: tornado
Requires-Dist: tornado ; extra == 'tornado'
